melisdk/__init__.py
melisdk/config.py
melisdk/meli.py
melisdk/ssl_helper.py
melisdk-0.1.3.dist-info/LICENSE
melisdk-0.1.3.dist-info/METADATA
melisdk-0.1.3.dist-info/WHEEL
melisdk-0.1.3.dist-info/top_level.txt
melisdk-0.1.3.dist-info/RECORD
