Metadata-Version: 2.1
Name: melisdk
Version: 0.1.3
Summary: A copy of MercadoLibre python SDK, but works
Home-page: https://github.com/dany2691/melisdk
Author: Daniel Omar Vergara Pérez
Author-email: daniel.omar.vergara@gmail.com
License: MIT
Platform: UNKNOWN
Classifier: License :: OSI Approved :: MIT License
Classifier: Programming Language :: Python :: 3.5
Classifier: Programming Language :: Python :: 3.6
Classifier: Programming Language :: Python :: 3.7
Classifier: Programming Language :: Python :: Implementation :: CPython
Classifier: Programming Language :: Python :: Implementation :: PyPy
Requires-Dist: requests (>=2.22.0)
